escape/__init__.py
escape/client.py
escape/globals.py
escape/py.typed
escape/_internal/__init__.py
escape/_internal/api.py
escape/_internal/batch.py
escape/_internal/cache_manager.py
escape/_internal/cleanup.py
escape/_internal/enums.py
escape/_internal/logger.py
escape/_internal/cache/__init__.py
escape/_internal/cache/event_cache.py
escape/_internal/cache/state_builder.py
escape/_internal/events/__init__.py
escape/_internal/events/channels.py
escape/_internal/events/consumer.py
escape/_internal/resources/__init__.py
escape/_internal/resources/objects.py
escape/_internal/resources/objects.pyi
escape/_internal/resources/varps.py
escape/_internal/resources/varps.pyi
escape/_internal/scraper/__init__.py
escape/_internal/scraper/proxy_generator.py
escape/_internal/scraper/scraper.py
escape/_internal/updater/__init__.py
escape/_internal/updater/__main__.py
escape/_internal/updater/api.py
escape/_internal/updater/main.py
escape/_internal/updater/resources.py
escape/_internal/visualizer/__init__.py
escape/_internal/visualizer/capture.py
escape/_internal/visualizer/visualizer.py
escape/_internal/visualizer/window.py
escape/input/__init__.py
escape/input/drawing.py
escape/input/keyboard.py
escape/input/mouse.py
escape/input/runelite.py
escape/interactions/__init__.py
escape/interactions/menu.py
escape/interfaces/__init__.py
escape/interfaces/bank.py
escape/interfaces/fairy_ring.py
escape/navigation/__init__.py
escape/navigation/pathfinder.py
escape/navigation/walker.py
escape/player/__init__.py
escape/player/player.py
escape/tabs/__init__.py
escape/tabs/account.py
escape/tabs/combat.py
escape/tabs/emotes.py
escape/tabs/equipment.py
escape/tabs/friends.py
escape/tabs/grouping.py
escape/tabs/inventory.py
escape/tabs/logout.py
escape/tabs/magic.py
escape/tabs/music.py
escape/tabs/prayer.py
escape/tabs/progress.py
escape/tabs/settings.py
escape/tabs/skills.py
escape/types/__init__.py
escape/types/box.py
escape/types/circle.py
escape/types/gametab.py
escape/types/ground_item.py
escape_sdk-2.2.1.dist-info/METADATA
escape_sdk-2.2.1.dist-info/WHEEL
escape_sdk-2.2.1.dist-info/top_level.txt
escape_sdk-2.2.1.dist-info/RECORD
